schematics_factory/__init__.py
schematics_factory-0.1.0.dist-info/DESCRIPTION.rst
schematics_factory-0.1.0.dist-info/METADATA
schematics_factory-0.1.0.dist-info/RECORD
schematics_factory-0.1.0.dist-info/WHEEL
schematics_factory-0.1.0.dist-info/metadata.json
schematics_factory-0.1.0.dist-info/top_level.txt
